{
    "fluentMethods": true,
    "relationships": [],
    "fields": [
        {
            "fieldName": "description",
            "fieldType": "byte[]",
            "fieldTypeBlobContent": "text",
            "fieldValidateRules": [
                "required"
            ]
        },
        {
            "fieldName": "datePlayed",
            "fieldType": "ZonedDateTime",
            "fieldValidateRules": [
                "required"
            ]
        }
    ],
    "changelogDate": "20171117210628",
    "entityTableName": "game",
    "dto": "mapstruct",
    "pagination": "infinite-scroll",
    "service": "serviceImpl",
    "jpaMetamodelFiltering": false,
    "microserviceName": "fuzAPI"
}